gqpy/__init__.py
gqpy/gqpy.py
gqpy/spot/enums.py
gqpy/spot/static.py
gqpy/spot/live/handler.py
gqpy/spot/live/live.py
gqpy/storage/storage.py
gqpy/storage/storage_utils.py
gqpy/storage/utils/csv_utils.py
gqpy/storage/utils/mongo_utils.py
gqpy/symbols/format.py
gqpy/symbols/requests.py
gqpy/symbols/symbols.py
gqpy-1.3.1.dist-info/METADATA
gqpy-1.3.1.dist-info/WHEEL
gqpy-1.3.1.dist-info/licenses/LICENCE
gqpy-1.3.1.dist-info/RECORD
